RTL/Counter.v
module Counter#(
	parameter BIT_WIDTH = 8
)(
	input wire CounterClock,
	input wire [1:0] CounterEdge,
	input wire CounterClear,
	output wire Overflow,
	output reg [BIT_WIDTH-1:0] TCNT
);

localparam PROHIBITED 	= 2'b00;
localparam RISING_EDGE 	= 2'b01;
localparam FALLING_EDGE = 2'b10;
localparam BOTH_EDGES 	= 2'b11;

initial begin
	TCNT = 8'b0;
end

assign Overflow = (TCNT == 8'hff);

always@(posedge CounterClock or negedge CounterClock or posedge CounterClear) begin
	if(CounterClear) 
		TCNT <= 8'b0;
	else if(CounterEdge == PROHIBITED)
		TCNT <= TCNT;
	else if(CounterClock && CounterEdge == RISING_EDGE)
		TCNT <= TCNT + 1;
	else if(!CounterClock && CounterEdge == FALLING_EDGE)
		TCNT <= TCNT + 1;
	else if(CounterEdge == BOTH_EDGES)
		TCNT <= TCNT + 1;
	else 
		TCNT <= TCNT;
end


endmodule

Testbench/Counter_tb.v
module Counter_tb;

reg CounterClock;
reg [1:0] CounterEdge;
reg CounterClear;
wire Overflow;
wire [7:0] TCNT;

Counter #(.BIT_WIDTH(8)) Counter_u(
	.CounterClock(CounterClock),
	.CounterEdge(CounterEdge),
	.CounterClear(CounterClear),
	.Overflow(Overflow),
	.TCNT(TCNT)
);

initial begin
	$dumpfile("Output/Counter.vcd");
	$dumpvars(0, Counter_tb);
end

initial begin
	CounterClock = 0;
	CounterEdge = 2'b11;
	CounterClear = 0;

	#2000 $finish;
end

always #5 CounterClock = ~CounterClock;


endmodule

Output/Counter.vcd
$date
	Fri Jun 13 23:56:57 2025
$end
$version
	Icarus Verilog
$end
$timescale
	1s
$end
$scope module Counter_tb $end
$var wire 8 ! TCNT [7:0] $end
$var wire 1 " Overflow $end
$var reg 1 # CounterClear $end
$var reg 1 $ CounterClock $end
$var reg 2 % CounterEdge [1:0] $end
$scope module Counter_u $end
$var wire 1 # CounterClear $end
$var wire 1 $ CounterClock $end
$var wire 2 & CounterEdge [1:0] $end
$var wire 1 " Overflow $end
$var parameter 32 ' BIT_WIDTH $end
$var parameter 2 ( BOTH_EDGES $end
$var parameter 2 ) FALLING_EDGE $end
$var parameter 2 * PROHIBITED $end
$var parameter 2 + RISING_EDGE $end
$var reg 8 , TCNT [7:0] $end
$upscope $end
$upscope $end
$enddefinitions $end
$comment Show the parameter values. $end
$dumpall
b1 +
b0 *
b10 )
b11 (
b1000 '
$end
#0
$dumpvars
b1 ,
b11 &
b11 %
0$
0#
0"
b1 !
$end
#5
b10 !
b10 ,
1$
#10
b11 !
b11 ,
0$
#15
b100 !
b100 ,
1$
#20
b101 !
b101 ,
0$
#25
b110 !
b110 ,
1$
#30
b111 !
b111 ,
0$
#35
b1000 !
b1000 ,
1$
#40
b1001 !
b1001 ,
0$
#45
b1010 !
b1010 ,
1$
#50
b1011 !
b1011 ,
0$
#55
b1100 !
b1100 ,
1$
#60
b1101 !
b1101 ,
0$
#65
b1110 !
b1110 ,
1$
#70
b1111 !
b1111 ,
0$
#75
b10000 !
b10000 ,
1$
#80
b10001 !
b10001 ,
0$
#85
b10010 !
b10010 ,
1$
#90
b10011 !
b10011 ,
0$
#95
b10100 !
b10100 ,
1$
#100
b10101 !
b10101 ,
0$
#105
b10110 !
b10110 ,
1$
#110
b10111 !
b10111 ,
0$
#115
b11000 !
b11000 ,
1$
#120
b11001 !
b11001 ,
0$
#125
b11010 !
b11010 ,
1$
#130
b11011 !
b11011 ,
0$
#135
b11100 !
b11100 ,
1$
#140
b11101 !
b11101 ,
0$
#145
b11110 !
b11110 ,
1$
#150
b11111 !
b11111 ,
0$
#155
b100000 !
b100000 ,
1$
#160
b100001 !
b100001 ,
0$
#165
b100010 !
b100010 ,
1$
#170
b100011 !
b100011 ,
0$
#175
b100100 !
b100100 ,
1$
#180
b100101 !
b100101 ,
0$
#185
b100110 !
b100110 ,
1$
#190
b100111 !
b100111 ,
0$
#195
b101000 !
b101000 ,
1$
#200
b101001 !
b101001 ,
0$
#205
b101010 !
b101010 ,
1$
#210
b101011 !
b101011 ,
0$
#215
b101100 !
b101100 ,
1$
#220
b101101 !
b101101 ,
0$
#225
b101110 !
b101110 ,
1$
#230
b101111 !
b101111 ,
0$
#235
b110000 !
b110000 ,
1$
#240
b110001 !
b110001 ,
0$
#245
b110010 !
b110010 ,
1$
#250
b110011 !
b110011 ,
0$
#255
b110100 !
b110100 ,
1$
#260
b110101 !
b110101 ,
0$
#265
b110110 !
b110110 ,
1$
#270
b110111 !
b110111 ,
0$
#275
b111000 !
b111000 ,
1$
#280
b111001 !
b111001 ,
0$
#285
b111010 !
b111010 ,
1$
#290
b111011 !
b111011 ,
0$
#295
b111100 !
b111100 ,
1$
#300
b111101 !
b111101 ,
0$
#305
b111110 !
b111110 ,
1$
#310
b111111 !
b111111 ,
0$
#315
b1000000 !
b1000000 ,
1$
#320
b1000001 !
b1000001 ,
0$
#325
b1000010 !
b1000010 ,
1$
#330
b1000011 !
b1000011 ,
0$
#335
b1000100 !
b1000100 ,
1$
#340
b1000101 !
b1000101 ,
0$
#345
b1000110 !
b1000110 ,
1$
#350
b1000111 !
b1000111 ,
0$
#355
b1001000 !
b1001000 ,
1$
#360
b1001001 !
b1001001 ,
0$
#365
b1001010 !
b1001010 ,
1$
#370
b1001011 !
b1001011 ,
0$
#375
b1001100 !
b1001100 ,
1$
#380
b1001101 !
b1001101 ,
0$
#385
b1001110 !
b1001110 ,
1$
#390
b1001111 !
b1001111 ,
0$
#395
b1010000 !
b1010000 ,
1$
#400
b1010001 !
b1010001 ,
0$
#405
b1010010 !
b1010010 ,
1$
#410
b1010011 !
b1010011 ,
0$
#415
b1010100 !
b1010100 ,
1$
#420
b1010101 !
b1010101 ,
0$
#425
b1010110 !
b1010110 ,
1$
#430
b1010111 !
b1010111 ,
0$
#435
b1011000 !
b1011000 ,
1$
#440
b1011001 !
b1011001 ,
0$
#445
b1011010 !
b1011010 ,
1$
#450
b1011011 !
b1011011 ,
0$
#455
b1011100 !
b1011100 ,
1$
#460
b1011101 !
b1011101 ,
0$
#465
b1011110 !
b1011110 ,
1$
#470
b1011111 !
b1011111 ,
0$
#475
b1100000 !
b1100000 ,
1$
#480
b1100001 !
b1100001 ,
0$
#485
b1100010 !
b1100010 ,
1$
#490
b1100011 !
b1100011 ,
0$
#495
b1100100 !
b1100100 ,
1$
#500
b1100101 !
b1100101 ,
0$
#505
b1100110 !
b1100110 ,
1$
#510
b1100111 !
b1100111 ,
0$
#515
b1101000 !
b1101000 ,
1$
#520
b1101001 !
b1101001 ,
0$
#525
b1101010 !
b1101010 ,
1$
#530
b1101011 !
b1101011 ,
0$
#535
b1101100 !
b1101100 ,
1$
#540
b1101101 !
b1101101 ,
0$
#545
b1101110 !
b1101110 ,
1$
#550
b1101111 !
b1101111 ,
0$
#555
b1110000 !
b1110000 ,
1$
#560
b1110001 !
b1110001 ,
0$
#565
b1110010 !
b1110010 ,
1$
#570
b1110011 !
b1110011 ,
0$
#575
b1110100 !
b1110100 ,
1$
#580
b1110101 !
b1110101 ,
0$
#585
b1110110 !
b1110110 ,
1$
#590
b1110111 !
b1110111 ,
0$
#595
b1111000 !
b1111000 ,
1$
#600
b1111001 !
b1111001 ,
0$
#605
b1111010 !
b1111010 ,
1$
#610
b1111011 !
b1111011 ,
0$
#615
b1111100 !
b1111100 ,
1$
#620
b1111101 !
b1111101 ,
0$
#625
b1111110 !
b1111110 ,
1$
#630
b1111111 !
b1111111 ,
0$
#635
b10000000 !
b10000000 ,
1$
#640
b10000001 !
b10000001 ,
0$
#645
b10000010 !
b10000010 ,
1$
#650
b10000011 !
b10000011 ,
0$
#655
b10000100 !
b10000100 ,
1$
#660
b10000101 !
b10000101 ,
0$
#665
b10000110 !
b10000110 ,
1$
#670
b10000111 !
b10000111 ,
0$
#675
b10001000 !
b10001000 ,
1$
#680
b10001001 !
b10001001 ,
0$
#685
b10001010 !
b10001010 ,
1$
#690
b10001011 !
b10001011 ,
0$
#695
b10001100 !
b10001100 ,
1$
#700
b10001101 !
b10001101 ,
0$
#705
b10001110 !
b10001110 ,
1$
#710
b10001111 !
b10001111 ,
0$
#715
b10010000 !
b10010000 ,
1$
#720
b10010001 !
b10010001 ,
0$
#725
b10010010 !
b10010010 ,
1$
#730
b10010011 !
b10010011 ,
0$
#735
b10010100 !
b10010100 ,
1$
#740
b10010101 !
b10010101 ,
0$
#745
b10010110 !
b10010110 ,
1$
#750
b10010111 !
b10010111 ,
0$
#755
b10011000 !
b10011000 ,
1$
#760
b10011001 !
b10011001 ,
0$
#765
b10011010 !
b10011010 ,
1$
#770
b10011011 !
b10011011 ,
0$
#775
b10011100 !
b10011100 ,
1$
#780
b10011101 !
b10011101 ,
0$
#785
b10011110 !
b10011110 ,
1$
#790
b10011111 !
b10011111 ,
0$
#795
b10100000 !
b10100000 ,
1$
#800
b10100001 !
b10100001 ,
0$
#805
b10100010 !
b10100010 ,
1$
#810
b10100011 !
b10100011 ,
0$
#815
b10100100 !
b10100100 ,
1$
#820
b10100101 !
b10100101 ,
0$
#825
b10100110 !
b10100110 ,
1$
#830
b10100111 !
b10100111 ,
0$
#835
b10101000 !
b10101000 ,
1$
#840
b10101001 !
b10101001 ,
0$
#845
b10101010 !
b10101010 ,
1$
#850
b10101011 !
b10101011 ,
0$
#855
b10101100 !
b10101100 ,
1$
#860
b10101101 !
b10101101 ,
0$
#865
b10101110 !
b10101110 ,
1$
#870
b10101111 !
b10101111 ,
0$
#875
b10110000 !
b10110000 ,
1$
#880
b10110001 !
b10110001 ,
0$
#885
b10110010 !
b10110010 ,
1$
#890
b10110011 !
b10110011 ,
0$
#895
b10110100 !
b10110100 ,
1$
#900
b10110101 !
b10110101 ,
0$
#905
b10110110 !
b10110110 ,
1$
#910
b10110111 !
b10110111 ,
0$
#915
b10111000 !
b10111000 ,
1$
#920
b10111001 !
b10111001 ,
0$
#925
b10111010 !
b10111010 ,
1$
#930
b10111011 !
b10111011 ,
0$
#935
b10111100 !
b10111100 ,
1$
#940
b10111101 !
b10111101 ,
0$
#945
b10111110 !
b10111110 ,
1$
#950
b10111111 !
b10111111 ,
0$
#955
b11000000 !
b11000000 ,
1$
#960
b11000001 !
b11000001 ,
0$
#965
b11000010 !
b11000010 ,
1$
#970
b11000011 !
b11000011 ,
0$
#975
b11000100 !
b11000100 ,
1$
#980
b11000101 !
b11000101 ,
0$
#985
b11000110 !
b11000110 ,
1$
#990
b11000111 !
b11000111 ,
0$
#995
b11001000 !
b11001000 ,
1$
#1000
b11001001 !
b11001001 ,
0$
#1005
b11001010 !
b11001010 ,
1$
#1010
b11001011 !
b11001011 ,
0$
#1015
b11001100 !
b11001100 ,
1$
#1020
b11001101 !
b11001101 ,
0$
#1025
b11001110 !
b11001110 ,
1$
#1030
b11001111 !
b11001111 ,
0$
#1035
b11010000 !
b11010000 ,
1$
#1040
b11010001 !
b11010001 ,
0$
#1045
b11010010 !
b11010010 ,
1$
#1050
b11010011 !
b11010011 ,
0$
#1055
b11010100 !
b11010100 ,
1$
#1060
b11010101 !
b11010101 ,
0$
#1065
b11010110 !
b11010110 ,
1$
#1070
b11010111 !
b11010111 ,
0$
#1075
b11011000 !
b11011000 ,
1$
#1080
b11011001 !
b11011001 ,
0$
#1085
b11011010 !
b11011010 ,
1$
#1090
b11011011 !
b11011011 ,
0$
#1095
b11011100 !
b11011100 ,
1$
#1100
b11011101 !
b11011101 ,
0$
#1105
b11011110 !
b11011110 ,
1$
#1110
b11011111 !
b11011111 ,
0$
#1115
b11100000 !
b11100000 ,
1$
#1120
b11100001 !
b11100001 ,
0$
#1125
b11100010 !
b11100010 ,
1$
#1130
b11100011 !
b11100011 ,
0$
#1135
b11100100 !
b11100100 ,
1$
#1140
b11100101 !
b11100101 ,
0$
#1145
b11100110 !
b11100110 ,
1$
#1150
b11100111 !
b11100111 ,
0$
#1155
b11101000 !
b11101000 ,
1$
#1160
b11101001 !
b11101001 ,
0$
#1165
b11101010 !
b11101010 ,
1$
#1170
b11101011 !
b11101011 ,
0$
#1175
b11101100 !
b11101100 ,
1$
#1180
b11101101 !
b11101101 ,
0$
#1185
b11101110 !
b11101110 ,
1$
#1190
b11101111 !
b11101111 ,
0$
#1195
b11110000 !
b11110000 ,
1$
#1200
b11110001 !
b11110001 ,
0$
#1205
b11110010 !
b11110010 ,
1$
#1210
b11110011 !
b11110011 ,
0$
#1215
b11110100 !
b11110100 ,
1$
#1220
b11110101 !
b11110101 ,
0$
#1225
b11110110 !
b11110110 ,
1$
#1230
b11110111 !
b11110111 ,
0$
#1235
b11111000 !
b11111000 ,
1$
#1240
b11111001 !
b11111001 ,
0$
#1245
b11111010 !
b11111010 ,
1$
#1250
b11111011 !
b11111011 ,
0$
#1255
b11111100 !
b11111100 ,
1$
#1260
b11111101 !
b11111101 ,
0$
#1265
b11111110 !
b11111110 ,
1$
#1270
1"
b11111111 !
b11111111 ,
0$
#1275
0"
b0 !
b0 ,
1$
#1280
b1 !
b1 ,
0$
#1285
b10 !
b10 ,
1$
#1290
b11 !
b11 ,
0$
#1295
b100 !
b100 ,
1$
#1300
b101 !
b101 ,
0$
#1305
b110 !
b110 ,
1$
#1310
b111 !
b111 ,
0$
#1315
b1000 !
b1000 ,
1$
#1320
b1001 !
b1001 ,
0$
#1325
b1010 !
b1010 ,
1$
#1330
b1011 !
b1011 ,
0$
#1335
b1100 !
b1100 ,
1$
#1340
b1101 !
b1101 ,
0$
#1345
b1110 !
b1110 ,
1$
#1350
b1111 !
b1111 ,
0$
#1355
b10000 !
b10000 ,
1$
#1360
b10001 !
b10001 ,
0$
#1365
b10010 !
b10010 ,
1$
#1370
b10011 !
b10011 ,
0$
#1375
b10100 !
b10100 ,
1$
#1380
b10101 !
b10101 ,
0$
#1385
b10110 !
b10110 ,
1$
#1390
b10111 !
b10111 ,
0$
#1395
b11000 !
b11000 ,
1$
#1400
b11001 !
b11001 ,
0$
#1405
b11010 !
b11010 ,
1$
#1410
b11011 !
b11011 ,
0$
#1415
b11100 !
b11100 ,
1$
#1420
b11101 !
b11101 ,
0$
#1425
b11110 !
b11110 ,
1$
#1430
b11111 !
b11111 ,
0$
#1435
b100000 !
b100000 ,
1$
#1440
b100001 !
b100001 ,
0$
#1445
b100010 !
b100010 ,
1$
#1450
b100011 !
b100011 ,
0$
#1455
b100100 !
b100100 ,
1$
#1460
b100101 !
b100101 ,
0$
#1465
b100110 !
b100110 ,
1$
#1470
b100111 !
b100111 ,
0$
#1475
b101000 !
b101000 ,
1$
#1480
b101001 !
b101001 ,
0$
#1485
b101010 !
b101010 ,
1$
#1490
b101011 !
b101011 ,
0$
#1495
b101100 !
b101100 ,
1$
#1500
b101101 !
b101101 ,
0$
#1505
b101110 !
b101110 ,
1$
#1510
b101111 !
b101111 ,
0$
#1515
b110000 !
b110000 ,
1$
#1520
b110001 !
b110001 ,
0$
#1525
b110010 !
b110010 ,
1$
#1530
b110011 !
b110011 ,
0$
#1535
b110100 !
b110100 ,
1$
#1540
b110101 !
b110101 ,
0$
#1545
b110110 !
b110110 ,
1$
#1550
b110111 !
b110111 ,
0$
#1555
b111000 !
b111000 ,
1$
#1560
b111001 !
b111001 ,
0$
#1565
b111010 !
b111010 ,
1$
#1570
b111011 !
b111011 ,
0$
#1575
b111100 !
b111100 ,
1$
#1580
b111101 !
b111101 ,
0$
#1585
b111110 !
b111110 ,
1$
#1590
b111111 !
b111111 ,
0$
#1595
b1000000 !
b1000000 ,
1$
#1600
b1000001 !
b1000001 ,
0$
#1605
b1000010 !
b1000010 ,
1$
#1610
b1000011 !
b1000011 ,
0$
#1615
b1000100 !
b1000100 ,
1$
#1620
b1000101 !
b1000101 ,
0$
#1625
b1000110 !
b1000110 ,
1$
#1630
b1000111 !
b1000111 ,
0$
#1635
b1001000 !
b1001000 ,
1$
#1640
b1001001 !
b1001001 ,
0$
#1645
b1001010 !
b1001010 ,
1$
#1650
b1001011 !
b1001011 ,
0$
#1655
b1001100 !
b1001100 ,
1$
#1660
b1001101 !
b1001101 ,
0$
#1665
b1001110 !
b1001110 ,
1$
#1670
b1001111 !
b1001111 ,
0$
#1675
b1010000 !
b1010000 ,
1$
#1680
b1010001 !
b1010001 ,
0$
#1685
b1010010 !
b1010010 ,
1$
#1690
b1010011 !
b1010011 ,
0$
#1695
b1010100 !
b1010100 ,
1$
#1700
b1010101 !
b1010101 ,
0$
#1705
b1010110 !
b1010110 ,
1$
#1710
b1010111 !
b1010111 ,
0$
#1715
b1011000 !
b1011000 ,
1$
#1720
b1011001 !
b1011001 ,
0$
#1725
b1011010 !
b1011010 ,
1$
#1730
b1011011 !
b1011011 ,
0$
#1735
b1011100 !
b1011100 ,
1$
#1740
b1011101 !
b1011101 ,
0$
#1745
b1011110 !
b1011110 ,
1$
#1750
b1011111 !
b1011111 ,
0$
#1755
b1100000 !
b1100000 ,
1$
#1760
b1100001 !
b1100001 ,
0$
#1765
b1100010 !
b1100010 ,
1$
#1770
b1100011 !
b1100011 ,
0$
#1775
b1100100 !
b1100100 ,
1$
#1780
b1100101 !
b1100101 ,
0$
#1785
b1100110 !
b1100110 ,
1$
#1790
b1100111 !
b1100111 ,
0$
#1795
b1101000 !
b1101000 ,
1$
#1800
b1101001 !
b1101001 ,
0$
#1805
b1101010 !
b1101010 ,
1$
#1810
b1101011 !
b1101011 ,
0$
#1815
b1101100 !
b1101100 ,
1$
#1820
b1101101 !
b1101101 ,
0$
#1825
b1101110 !
b1101110 ,
1$
#1830
b1101111 !
b1101111 ,
0$
#1835
b1110000 !
b1110000 ,
1$
#1840
b1110001 !
b1110001 ,
0$
#1845
b1110010 !
b1110010 ,
1$
#1850
b1110011 !
b1110011 ,
0$
#1855
b1110100 !
b1110100 ,
1$
#1860
b1110101 !
b1110101 ,
0$
#1865
b1110110 !
b1110110 ,
1$
#1870
b1110111 !
b1110111 ,
0$
#1875
b1111000 !
b1111000 ,
1$
#1880
b1111001 !
b1111001 ,
0$
#1885
b1111010 !
b1111010 ,
1$
#1890
b1111011 !
b1111011 ,
0$
#1895
b1111100 !
b1111100 ,
1$
#1900
b1111101 !
b1111101 ,
0$
#1905
b1111110 !
b1111110 ,
1$
#1910
b1111111 !
b1111111 ,
0$
#1915
b10000000 !
b10000000 ,
1$
#1920
b10000001 !
b10000001 ,
0$
#1925
b10000010 !
b10000010 ,
1$
#1930
b10000011 !
b10000011 ,
0$
#1935
b10000100 !
b10000100 ,
1$
#1940
b10000101 !
b10000101 ,
0$
#1945
b10000110 !
b10000110 ,
1$
#1950
b10000111 !
b10000111 ,
0$
#1955
b10001000 !
b10001000 ,
1$
#1960
b10001001 !
b10001001 ,
0$
#1965
b10001010 !
b10001010 ,
1$
#1970
b10001011 !
b10001011 ,
0$
#1975
b10001100 !
b10001100 ,
1$
#1980
b10001101 !
b10001101 ,
0$
#1985
b10001110 !
b10001110 ,
1$
#1990
b10001111 !
b10001111 ,
0$
#1995
b10010000 !
b10010000 ,
1$
#2000
b10010001 !
b10010001 ,
0$
