RTL/LogicControl.v
module LogicControl#(
	parameter BIT_WIDTH = 8,
	parameter CLK_SELECT_BIT_WIDTH = 4
)(
	input wire TMRI0,
	input wire TMRI1,

	input wire [BIT_WIDTH-1:0] TCR_0,
	input wire [BIT_WIDTH-1:0] TCR_1,
	input wire [BIT_WIDTH-1:0] TCCR_0,
	input wire [BIT_WIDTH-1:0] TCCR_1,
	input wire [BIT_WIDTH-1:0] TCSR_0,
	input wire [BIT_WIDTH-1:0] TCSR_1,

	input wire CompareMatchA0,
	input wire CompareMatchA1,
	input wire CompareMatchB0,
	input wire CompareMatchB1,
	input wire Overflow0,
	input wire Overflow1,
	output wire CounterClear0,
	output wire CounterClear1,

	output reg CMIA0,
	output reg CMIA1,
	output reg CMIB0,
	output reg CMIB1,
	output reg OVI0,
	output reg OVI1,

	output reg TMO0,
	output reg TMO1,
	output reg ADC_REQUEST,

	output wire [CLK_SELECT_BIT_WIDTH-1:0] clock_select_0,
	output wire [CLK_SELECT_BIT_WIDTH-1:0] clock_select_1
);



//TCR
assign CMIEB_0 	= TCR_0[7];
assign CMIEA_0 	= TCR_0[6];
assign OVIE_0 	= TCR_0[5];
assign CCLR0_0 	= TCR_0[4];
assign CCLR1_0 	= TCR_0[3];
assign CKS2_0 	= TCR_0[2];
assign CKS1_0 	= TCR_0[1];
assign CKS0_0 	= TCR_0[0];

assign CMIEB_1 	= TCR_1[7];
assign CMIEA_1 	= TCR_1[6];
assign OVIE_1 	= TCR_1[5];
assign CCLR0_1 	= TCR_1[4];
assign CCLR1_1 	= TCR_1[3];
assign CKS2_1 	= TCR_1[2];
assign CKS1_1 	= TCR_1[1];
assign CKS0_1 	= TCR_1[0];

//TCCR
assign TMRIS_0 	= TCCR_0[3];
assign ICKS1_0 	= TCCR_0[1];
assign ICKS0_0 	= TCCR_0[0];

assign TMRIS_1 	= TCCR_1[3];
assign ICKS1_1 	= TCCR_1[1];
assign ICKS0_1 	= TCCR_1[0];

//TCSR
assign CMFB_0 	= TCSR_0[7];
assign CMFA_0 	= TCSR_0[6];
assign OVF_0 	= TCSR_0[5];
assign ADTE_0 	= TCSR_0[4];
assign OS3_0 	= TCSR_0[3];
assign OS2_0 	= TCSR_0[2];
assign OS1_0 	= TCSR_0[1];
assign OS0_0 	= TCSR_0[0];


assign CMFB_1 	= TCSR_1[7];
assign CMFA_1 	= TCSR_1[6];
assign OVF_1 	= TCSR_1[5];
assign OS3_1 	= TCSR_1[3];
assign OS2_1 	= TCSR_1[2];
assign OS1_1 	= TCSR_1[1];
assign OS0_1 	= TCSR_1[0];

//Channel 0:
assign pulse_rst_0 = TMRIS_0 && TMRI0;
reg edge_rst_0;
always@(posedge TMRI0) begin
	edge_rst_0 <= TMRIS_0;
end
assign CounterClear0 = 	({CCLR1_0, CCLR0_0} == 2'b00)? 0 :
			({CCLR1_0, CCLR0_0} == 2'b01)? CompareMatchA0 :
			({CCLR1_0, CCLR0_0} == 2'b10)? CompareMatchB0 :
			(TMRIS_0) ? edge_rst_0 : pulse_rst_0;
//Channel 1:
assign pulse_rst_1 = TMRIS_1 && TMRI1;
reg edge_rst_1;
always@(posedge TMRI0) begin
	edge_rst_1 <= TMRIS_1;
end
assign CounterClear1 = 	({CCLR1_1, CCLR0_1} == 2'b00)? 0 :
			({CCLR1_1, CCLR0_1} == 2'b01)? CompareMatchA1 :
			({CCLR1_1, CCLR0_1} == 2'b10)? CompareMatchB1 :
			(TMRIS_1) ? edge_rst_1 : pulse_rst_1;
always@(*) begin
	//Channel 0:
	CMIB0 	<= CMFB_0 & CMIEB_0;
	CMIA0 	<= CMFA_0 & CMIEA_0;
	OVI0 	<= OVF_0 & OVIE_0;
	
	//Channel 1:
	CMIB1 	<= CMFB_1 & CMIEB_1;
	CMIA1 	<= CMFA_1 & CMIEA_1;
	OVI1 	<= OVF_1 & OVIE_1;
end

always@(*) begin
	ADC_REQUEST <= (ADTE_0)? CompareMatchA0 : !CompareMatchA0;
	//Channel 0
	case({OS3_0, OS2_0, OS1_0, OS0_0}) 
		4'b0000: TMO0 <= TMRI0;
		4'b0001: TMO0 <= !CompareMatchA0;
		4'b0010: TMO0 <= CompareMatchA0;
		4'b0011: TMO0 <= (CompareMatchA0) ? ~TMO0 : TMO0;
		4'b0100: TMO0 <= !CompareMatchB0;
		4'b0101: TMO0 <= !CompareMatchA0 | !CompareMatchB0;
		4'b0110: TMO0 <= !CompareMatchB0 | CompareMatchA0;
		4'b0111: TMO0 <= (CompareMatchA0) ? ~TMO0 : !CompareMatchB0;
		4'b1000: TMO0 <= CompareMatchB0;
		4'b1001: TMO0 <= CompareMatchB0 | !CompareMatchA0;
		4'b1010: TMO0 <= CompareMatchA0 | CompareMatchB0;
		4'b1011: TMO0 <= (CompareMatchA0) ? ~TMO0 : CompareMatchB0;
		4'b1100: TMO0 <= (CompareMatchB0) ? ~TMO0 : TMO0;
		4'b1101: TMO0 <= (CompareMatchB0) ? ~TMO0 : !CompareMatchA0;
		4'b1110: TMO0 <= (CompareMatchB0) ? ~TMO0 : CompareMatchA0;
		4'b1111: TMO0 <= (CompareMatchA0 || CompareMatchB0) ? ~TMO0 : TMO0;
		default: TMO0 <= TMO0;
	endcase
	//Channel 1
	case({OS3_1, OS2_1, OS1_1, OS0_1}) 
		4'b0000: TMO1 <= TMRI1;
		4'b0001: TMO1 <= !CompareMatchA1;
		4'b0010: TMO1 <= CompareMatchA1;
		4'b0011: TMO1 <= (CompareMatchA1) ? ~TMO1 : TMO1;
		4'b0100: TMO1 <= !CompareMatchB1;
		4'b0101: TMO1 <= !CompareMatchA1 | !CompareMatchB1;
		4'b0110: TMO1 <= !CompareMatchB1 | CompareMatchA1;
		4'b0111: TMO1 <= (CompareMatchA1) ? ~TMO1 : !CompareMatchB1;
		4'b1000: TMO1 <= CompareMatchB1;
		4'b1001: TMO1 <= CompareMatchB1 | !CompareMatchA1;
		4'b1010: TMO1 <= CompareMatchA1 | CompareMatchB1;
		4'b1011: TMO1 <= (CompareMatchA1) ? ~TMO1 : CompareMatchB1;
		4'b1100: TMO1 <= (CompareMatchB1) ? ~TMO1 : TMO1;
		4'b1101: TMO1 <= (CompareMatchB1) ? ~TMO1 : !CompareMatchA1;
		4'b1110: TMO1 <= (CompareMatchB1) ? ~TMO1 : CompareMatchA1;
		4'b1111: TMO1 <= (CompareMatchA1 || CompareMatchB1) ? ~TMO1 : TMO1;
		default: TMO1 <= TMO1;
	endcase
end

assign clock_select_0 = {CKS2_0, CKS1_0, CKS0_0, ICKS1_0, ICKS0_0};
assign clock_select_1 = {CKS2_1, CKS1_1, CKS0_1, ICKS1_1, ICKS0_1};

endmodule

Testbench/LogicControl_tb.v
module LogicControl_tb;

reg TMRI0;
reg TMRI1;

reg [7:0] TCR_0;
reg [7:0] TCR_1;
reg [7:0] TCCR_0;
reg [7:0] TCCR_1;
reg [7:0] TCSR_0;
reg [7:0] TCSR_1;

reg CompareMatchA0;
reg CompareMatchA1;
reg CompareMatchB0;
reg CompareMatchB1;
reg Overflow0;
reg Overflow1;


wire CMIA0;
wire CMIA1;
wire CMIB0;
wire CMIB1;
wire OVI0;
wire OVI1;

wire TMO0;
wire TMO1;
wire ADC_REQUEST;

wire [4:0] clock_select_0;
wire [4:0] clock_select_1;


LogicControl #(.BIT_WIDTH(8), .CLK_SELECT_BIT_WIDTH(5)) LogicControl_u(
	.TMRI0(TMRI0),
	.TMRI1(TMRI1),
	.TCR_0(TCR_0),
	.TCR_1(TCR_1),
	.TCCR_0(TCCR_0),
	.TCCR_1(TCCR_1),
	.TCSR_0(TCSR_0),
	.TCSR_1(TCSR_1),
	.CompareMatchA0(CompareMatchA0),
	.CompareMatchA1(CompareMatchA1),
	.CompareMatchB0(CompareMatchB0),
	.CompareMatchB1(CompareMatchB1),
	.CMIA0(CMIA0),
	.CMIA1(CMIA1),
	.CMIB0(CMIB0),
	.CMIB1(CMIB1),
	.OVI0(OVI0),
	.OVI1(OVI1),
	.TMO0(TMO0),
	.TMO1(TMO1),
	.ADC_REQUEST(ADC_REQUEST),
	.clock_select_0(clock_select_0),
	.clock_select_1(clock_select_1)
);

initial begin
	$dumpfile("Output/LogicControl.vcd");
	$dumpvars(0, LogicControl_tb);
end


always #5 CompareMatchA0 = ~CompareMatchA0;
always #10 CompareMatchB0 = ~CompareMatchB0;


initial begin 
	TMRI0 <= 0;
	TMRI1 <= 0;
	TCR_0 <= 8'b0;
	TCR_1 <= 8'b0;
	TCCR_0 <= 8'b0;
	TCCR_1 <= 8'b0;
	TCSR_0 <= 8'b0;
	TCSR_1 <= 8'b00010000;
	
	CompareMatchA0 <= 0;
	CompareMatchA1 <= 0;
 	CompareMatchB0 <= 0;
 	CompareMatchB1 <= 0;
	Overflow0      <= 0;
	Overflow1      <= 0;


	#20 TCSR_0 = 8'b00000110;
	//TCR_0 <= 8'b00001000;


	#1000 $finish;
end

endmodule

Output/LogicControl.vcd
$date
	Sat Jun 14 21:38:03 2025
$end
$version
	Icarus Verilog
$end
$timescale
	1s
$end
$scope module LogicControl_tb $end
$var wire 5 ! clock_select_1 [4:0] $end
$var wire 5 " clock_select_0 [4:0] $end
$var wire 1 # TMO1 $end
$var wire 1 $ TMO0 $end
$var wire 1 % OVI1 $end
$var wire 1 & OVI0 $end
$var wire 1 ' CMIB1 $end
$var wire 1 ( CMIB0 $end
$var wire 1 ) CMIA1 $end
$var wire 1 * CMIA0 $end
$var wire 1 + ADC_REQUEST $end
$var reg 1 , CompareMatchA0 $end
$var reg 1 - CompareMatchA1 $end
$var reg 1 . CompareMatchB0 $end
$var reg 1 / CompareMatchB1 $end
$var reg 1 0 Overflow0 $end
$var reg 1 1 Overflow1 $end
$var reg 8 2 TCCR_0 [7:0] $end
$var reg 8 3 TCCR_1 [7:0] $end
$var reg 8 4 TCR_0 [7:0] $end
$var reg 8 5 TCR_1 [7:0] $end
$var reg 8 6 TCSR_0 [7:0] $end
$var reg 8 7 TCSR_1 [7:0] $end
$var reg 1 8 TMRI0 $end
$var reg 1 9 TMRI1 $end
$scope module LogicControl_u $end
$var wire 1 , CompareMatchA0 $end
$var wire 1 - CompareMatchA1 $end
$var wire 1 . CompareMatchB0 $end
$var wire 1 / CompareMatchB1 $end
$var wire 1 : Overflow0 $end
$var wire 1 ; Overflow1 $end
$var wire 8 < TCCR_0 [7:0] $end
$var wire 8 = TCCR_1 [7:0] $end
$var wire 8 > TCR_0 [7:0] $end
$var wire 8 ? TCR_1 [7:0] $end
$var wire 8 @ TCSR_0 [7:0] $end
$var wire 8 A TCSR_1 [7:0] $end
$var wire 1 8 TMRI0 $end
$var wire 1 9 TMRI1 $end
$var wire 1 B pulse_rst_0 $end
$var wire 1 C pulse_rst_1 $end
$var wire 5 D clock_select_1 [4:0] $end
$var wire 5 E clock_select_0 [4:0] $end
$var wire 1 F TMRIS_1 $end
$var wire 1 G TMRIS_0 $end
$var wire 1 H OVIE_1 $end
$var wire 1 I OVIE_0 $end
$var wire 1 J OVF_1 $end
$var wire 1 K OVF_0 $end
$var wire 1 L OS3_1 $end
$var wire 1 M OS3_0 $end
$var wire 1 N OS2_1 $end
$var wire 1 O OS2_0 $end
$var wire 1 P OS1_1 $end
$var wire 1 Q OS1_0 $end
$var wire 1 R OS0_1 $end
$var wire 1 S OS0_0 $end
$var wire 1 T ICKS1_1 $end
$var wire 1 U ICKS1_0 $end
$var wire 1 V ICKS0_1 $end
$var wire 1 W ICKS0_0 $end
$var wire 1 X CounterClear1 $end
$var wire 1 Y CounterClear0 $end
$var wire 1 Z CMIEB_1 $end
$var wire 1 [ CMIEB_0 $end
$var wire 1 \ CMIEA_1 $end
$var wire 1 ] CMIEA_0 $end
$var wire 1 ^ CMFB_1 $end
$var wire 1 _ CMFB_0 $end
$var wire 1 ` CMFA_1 $end
$var wire 1 a CMFA_0 $end
$var wire 1 b CKS2_1 $end
$var wire 1 c CKS2_0 $end
$var wire 1 d CKS1_1 $end
$var wire 1 e CKS1_0 $end
$var wire 1 f CKS0_1 $end
$var wire 1 g CKS0_0 $end
$var wire 1 h CCLR1_1 $end
$var wire 1 i CCLR1_0 $end
$var wire 1 j CCLR0_1 $end
$var wire 1 k CCLR0_0 $end
$var wire 1 l ADTE_0 $end
$var parameter 32 m BIT_WIDTH $end
$var parameter 32 n CLK_SELECT_BIT_WIDTH $end
$var reg 1 + ADC_REQUEST $end
$var reg 1 * CMIA0 $end
$var reg 1 ) CMIA1 $end
$var reg 1 ( CMIB0 $end
$var reg 1 ' CMIB1 $end
$var reg 1 & OVI0 $end
$var reg 1 % OVI1 $end
$var reg 1 $ TMO0 $end
$var reg 1 # TMO1 $end
$var reg 1 o edge_rst_0 $end
$var reg 1 p edge_rst_1 $end
$upscope $end
$upscope $end
$enddefinitions $end
$comment Show the parameter values. $end
$dumpall
b101 n
b1000 m
$end
#0
$dumpvars
xp
xo
0l
0k
0j
0i
0h
0g
0f
0e
0d
0c
0b
0a
0`
0_
0^
0]
0\
0[
0Z
0Y
0X
0W
0V
0U
0T
0S
0R
0Q
0P
0O
0N
0M
0L
0K
0J
0I
0H
0G
0F
b0 E
b0 D
0C
0B
b10000 A
b0 @
b0 ?
b0 >
b0 =
b0 <
z;
z:
09
08
b10000 7
b0 6
b0 5
b0 4
b0 3
b0 2
01
00
0/
0.
0-
0,
1+
0*
0)
0(
0'
0&
0%
0$
0#
b0 "
b0 !
$end
#5
0+
1,
#10
1+
0,
1.
#15
0+
1,
#20
1$
1+
1O
1Q
0,
0.
b110 6
b110 @
#25
0+
1,
#30
0$
1+
0,
1.
#35
1$
0+
1,
#40
1+
0,
0.
#45
0+
1,
#50
0$
1+
0,
1.
#55
1$
0+
1,
#60
1+
0,
0.
#65
0+
1,
#70
0$
1+
0,
1.
#75
1$
0+
1,
#80
1+
0,
0.
#85
0+
1,
#90
0$
1+
0,
1.
#95
1$
0+
1,
#100
1+
0,
0.
#105
0+
1,
#110
0$
1+
0,
1.
#115
1$
0+
1,
#120
1+
0,
0.
#125
0+
1,
#130
0$
1+
0,
1.
#135
1$
0+
1,
#140
1+
0,
0.
#145
0+
1,
#150
0$
1+
0,
1.
#155
1$
0+
1,
#160
1+
0,
0.
#165
0+
1,
#170
0$
1+
0,
1.
#175
1$
0+
1,
#180
1+
0,
0.
#185
0+
1,
#190
0$
1+
0,
1.
#195
1$
0+
1,
#200
1+
0,
0.
#205
0+
1,
#210
0$
1+
0,
1.
#215
1$
0+
1,
#220
1+
0,
0.
#225
0+
1,
#230
0$
1+
0,
1.
#235
1$
0+
1,
#240
1+
0,
0.
#245
0+
1,
#250
0$
1+
0,
1.
#255
1$
0+
1,
#260
1+
0,
0.
#265
0+
1,
#270
0$
1+
0,
1.
#275
1$
0+
1,
#280
1+
0,
0.
#285
0+
1,
#290
0$
1+
0,
1.
#295
1$
0+
1,
#300
1+
0,
0.
#305
0+
1,
#310
0$
1+
0,
1.
#315
1$
0+
1,
#320
1+
0,
0.
#325
0+
1,
#330
0$
1+
0,
1.
#335
1$
0+
1,
#340
1+
0,
0.
#345
0+
1,
#350
0$
1+
0,
1.
#355
1$
0+
1,
#360
1+
0,
0.
#365
0+
1,
#370
0$
1+
0,
1.
#375
1$
0+
1,
#380
1+
0,
0.
#385
0+
1,
#390
0$
1+
0,
1.
#395
1$
0+
1,
#400
1+
0,
0.
#405
0+
1,
#410
0$
1+
0,
1.
#415
1$
0+
1,
#420
1+
0,
0.
#425
0+
1,
#430
0$
1+
0,
1.
#435
1$
0+
1,
#440
1+
0,
0.
#445
0+
1,
#450
0$
1+
0,
1.
#455
1$
0+
1,
#460
1+
0,
0.
#465
0+
1,
#470
0$
1+
0,
1.
#475
1$
0+
1,
#480
1+
0,
0.
#485
0+
1,
#490
0$
1+
0,
1.
#495
1$
0+
1,
#500
1+
0,
0.
#505
0+
1,
#510
0$
1+
0,
1.
#515
1$
0+
1,
#520
1+
0,
0.
#525
0+
1,
#530
0$
1+
0,
1.
#535
1$
0+
1,
#540
1+
0,
0.
#545
0+
1,
#550
0$
1+
0,
1.
#555
1$
0+
1,
#560
1+
0,
0.
#565
0+
1,
#570
0$
1+
0,
1.
#575
1$
0+
1,
#580
1+
0,
0.
#585
0+
1,
#590
0$
1+
0,
1.
#595
1$
0+
1,
#600
1+
0,
0.
#605
0+
1,
#610
0$
1+
0,
1.
#615
1$
0+
1,
#620
1+
0,
0.
#625
0+
1,
#630
0$
1+
0,
1.
#635
1$
0+
1,
#640
1+
0,
0.
#645
0+
1,
#650
0$
1+
0,
1.
#655
1$
0+
1,
#660
1+
0,
0.
#665
0+
1,
#670
0$
1+
0,
1.
#675
1$
0+
1,
#680
1+
0,
0.
#685
0+
1,
#690
0$
1+
0,
1.
#695
1$
0+
1,
#700
1+
0,
0.
#705
0+
1,
#710
0$
1+
0,
1.
#715
1$
0+
1,
#720
1+
0,
0.
#725
0+
1,
#730
0$
1+
0,
1.
#735
1$
0+
1,
#740
1+
0,
0.
#745
0+
1,
#750
0$
1+
0,
1.
#755
1$
0+
1,
#760
1+
0,
0.
#765
0+
1,
#770
0$
1+
0,
1.
#775
1$
0+
1,
#780
1+
0,
0.
#785
0+
1,
#790
0$
1+
0,
1.
#795
1$
0+
1,
#800
1+
0,
0.
#805
0+
1,
#810
0$
1+
0,
1.
#815
1$
0+
1,
#820
1+
0,
0.
#825
0+
1,
#830
0$
1+
0,
1.
#835
1$
0+
1,
#840
1+
0,
0.
#845
0+
1,
#850
0$
1+
0,
1.
#855
1$
0+
1,
#860
1+
0,
0.
#865
0+
1,
#870
0$
1+
0,
1.
#875
1$
0+
1,
#880
1+
0,
0.
#885
0+
1,
#890
0$
1+
0,
1.
#895
1$
0+
1,
#900
1+
0,
0.
#905
0+
1,
#910
0$
1+
0,
1.
#915
1$
0+
1,
#920
1+
0,
0.
#925
0+
1,
#930
0$
1+
0,
1.
#935
1$
0+
1,
#940
1+
0,
0.
#945
0+
1,
#950
0$
1+
0,
1.
#955
1$
0+
1,
#960
1+
0,
0.
#965
0+
1,
#970
0$
1+
0,
1.
#975
1$
0+
1,
#980
1+
0,
0.
#985
0+
1,
#990
0$
1+
0,
1.
#995
1$
0+
1,
#1000
1+
0,
0.
#1005
0+
1,
#1010
0$
1+
0,
1.
#1015
1$
0+
1,
#1020
1+
0,
0.
